CA FE BA BE 00 00 00 34 00 18 0A 00 04 00 14 09 00 03 00 15 07 00 16 07 00 17 01 00 01 61 01 00
01 49 01 00 06 3C 69 6E 69 74 3E 01 00 03 28 29 56 01 00 04 43 6F 64 65 01 00 0F 4C 69 6E 65 4E
75 6D 62 65 72 54 61 62 6C 65 01 00 12 4C 6F 63 61 6C 56 61 72 69 61 62 6C 65 54 61 62 6C 65 01
00 04 74 68 69 73 01 00 26 4C 63 6F 6D 2F 6B 65 76 69 6E 2F 73 74 75 64 79 2F 6A 76 6D 2F 62 79
74 65 63 6F 64 65 2F 4D 79 54 65 73 74 31 3B 01 00 04 67 65 74 41 01 00 03 28 29 49 01 00 04 73
65 74 41 01 00 04 28 49 29 56 01 00 0A 53 6F 75 72 63 65 46 69 6C 65 01 00 0C 4D 79 54 65 73 74
31 2E 6A 61 76 61 0C 00 07 00 08 0C 00 05 00 06 01 00 24 63 6F 6D 2F 6B 65 76 69 6E 2F 73 74 75
64 79 2F 6A 76 6D 2F 62 79 74 65 63 6F 64 65 2F 4D 79 54 65 73 74 31 01 00 10 6A 61 76 61 2F 6C
61 6E 67 2F 4F 62 6A 65 63 74 00 21 00 03 00 04 00 00 00 01 00 02 00 05 00 06 00 00 00 03 00 01
00 07 00 08 00 01 00 09 00 00 00 38 00 02 00 01 00 00 00 0A 2A B7 00 01 2A 04 B5 00 02 B1 00 00
00 02 00 0A 00 00 00 0A 00 02 00 00 00 0B 00 04 00 0D 00 0B 00 00 00 0C 00 01 00 00 00 0A 00 0C
00 0D 00 00 00 01 00 0E 00 0F 00 01 00 09 00 00 00 2F 00 01 00 01 00 00 00 05 2A B4 00 02 AC 00
00 00 02 00 0A 00 00 00 06 00 01 00 00 00 10 00 0B 00 00 00 0C 00 01 00 00 00 05 00 0C 00 0D 00
00 00 01 00 10 00 11 00 01 00 09 00 00 00 3E 00 02 00 02 00 00 00 06 2A 1B B5 00 02 B1 00 00 00
02 00 0A 00 00 00 0A 00 02 00 00 00 14 00 05 00 15 00 0B 00 00 00 16 00 02 00 00 00 06 00 0C 00
0D 00 00 00 00 00 06 00 05 00 06 00 01 00 01 00 12 00 00 00 02 00 13

字节码解读（可以对照javap -verbose查看）：
魔数（4字节）：CA FE BA BE
此版本号（2字节）：00 00（0）
主版本号（2字节）：00 34（52）
常量池数量（2字节）：00 18（24 - 1 = 23个）
常量池数组：
                              0A 00 04 00 14 09 00 03 00 15 07 00 16 07 00 17 01 00 01 61 01 00
01 49 01 00 06 3C 69 6E 69 74 3E 01 00 03 28 29 56 01 00 04 43 6F 64 65 01 00 0F 4C 69 6E 65 4E
75 6D 62 65 72 54 61 62 6C 65 01 00 12 4C 6F 63 61 6C 56 61 72 69 61 62 6C 65 54 61 62 6C 65 01
00 04 74 68 69 73 01 00 26 4C 63 6F 6D 2F 6B 65 76 69 6E 2F 73 74 75 64 79 2F 6A 76 6D 2F 62 79
74 65 63 6F 64 65 2F 4D 79 54 65 73 74 31 3B 01 00 04 67 65 74 41 01 00 03 28 29 49 01 00 04 73
65 74 41 01 00 04 28 49 29 56 01 00 0A 53 6F 75 72 63 65 46 69 6C 65 01 00 0C 4D 79 54 65 73 74
31 2E 6A 61 76 61 0C 00 07 00 08 0C 00 05 00 06 01 00 24 63 6F 6D 2F 6B 65 76 69 6E 2F 73 74 75
64 79 2F 6A 76 6D 2F 62 79 74 65 63 6F 64 65 2F 4D 79 54 65 73 74 31 01 00 10 6A 61 76 61 2F 6C
61 6E 67 2F 4F 62 6A 65 63 74
常量池数据需要对照常量池数据类型对照表来解析，第一个字节为数据类型（标签）；根据类型判断如何解析字节码
   #1 = Methodref          #4.#20         // java/lang/Object."<init>":()V
   #2 = Fieldref           #3.#21         // com/kevin/study/jvm/bytecode/MyTest1.a:I
   #3 = Class              #22            // com/kevin/study/jvm/bytecode/MyTest1
   #4 = Class              #23            // java/lang/Object
   #5 = Utf8               a
   #6 = Utf8               I
   #7 = Utf8               <init>
   #8 = Utf8               ()V
   #9 = Utf8               Code
  #10 = Utf8               LineNumberTable
  #11 = Utf8               LocalVariableTable
  #12 = Utf8               this
  #13 = Utf8               Lcom/kevin/study/jvm/bytecode/MyTest1;
  #14 = Utf8               getA
  #15 = Utf8               ()I
  #16 = Utf8               setA
  #17 = Utf8               (I)V
  #18 = Utf8               SourceFile
  #19 = Utf8               MyTest1.java
  #20 = NameAndType        #7:#8          // "<init>":()V
  #21 = NameAndType        #5:#6          // a:I
  #22 = Utf8               com/kevin/study/jvm/bytecode/MyTest1
  #23 = Utf8               java/lang/Object

类的访问控制权限（2字节）：00 21（public）
当前类名（2个字节）：00 03（常量池中的索引 #3）
父类名（2个字节）：00 04（常量池中的索引 #4）
接口数量（2个字节）：00 00（0，接下来的接口信息不占用该字节）

字段个数（2个字节）：00 01（1个）
字段信息：
    访问类型（2个字节）：00 02（provide）
    名称索引（2个字节）：00 05（#5 a）
    描述符（2个字节）：00 06（#6 I,int类型）
    属性个数（2个字节）：00 00（0，没有属性详细信息）

方法个数（2个字节）：00 03（3个方法）
方法信息：
     {
        访问类型（2个字节）：00 01（public）
        名称索引（2个字节）：00 07（#7 <init>方法，默认无参构造器）
        描述符（2个字节）：00 08（#8 ()V 无参，返回值void）
        属性个数（2个字节）：00 01（1个）
            属性名索引（2个字节）：00 09（#9 Code）
            属性长度（4个字节）：00 00 00 38（56个字节）
            属性信息：
            00 02 00 01 00 00 00 0A 2A B7 00 01 2A 04 B5 00 02 B1 00 00
            00 02 00 0A 00 00 00 0A 00 02 00 00 00 0B 00 04 00 0D 00 0B 00 00 00 0C 00 01 00 00 00 0A 00 0C
            00 0D 00 00
            {
                最大操作栈的深度（2个字节）：00 02（2）
                局部变量最大数目（2个字节）：00 01（1）
                方法占用字节数（4个字节）：00 00 00 0A（10个）
                    方法体（对应助记符）：
                    2A B7 00 01 2A 04 B5 00 02 B1
                    2A：aload_0
                    B7：invokespecial
                    00 01：#1  java/lang/Object."<init>"
                    2A：aload_0
                    04：iconst_1
                    B5：putfield
                    00 02：#2  com/kevin/study/jvm/bytecode/MyTest1.a
                    B1：return
                异常表（2个字节）：00 00（0，无异常信息）
                方法属性个数（2个字节）：00 02（2个）
                属性信息：
                {
                    属性名称（2个字节）：00 0A（#10 LineNumberTable）
                    属性长度（4个字节）：00 00 00 0A（10个字节）
                    参数个数（2个字节）：00 02（2）
                        {
                            字节码偏移量（2个字节）：00 00（0）
                            对应行号（2个字节）：00 0B（11行）
                        }，
                        {
                            字节码偏移量（2个字节）：00 04（4）
                            对应行号（2个字节）：00 0D（13行）
                        }
                }，
                {
                    属性名称（2个字节）：00 0B（#11 LocalVariableTable）
                    属性长度（4个字节）：00 00 00 0C（12个字节）
                    参数个数（2个字节）：00 01（1个）
                    {
                        开始偏移量（2个字节）：00 00（0）
                        长度（2个字节）：00 0A（10）
                        名称索引（2个字节）：00 0C（#12 this）
                        名字描述（2个字节）：00 0D（#13 Lcom/kevin/study/jvm/bytecode/MyTest1）
                        index（2个字节）：00 00
                    }
                }
            }
     }，
     {
        访问类型（2个字节）：00 01（public）
        名称索引（2个字节）：00 0E（#14 getA）
        描述符（2个字节）：00 0F（#15 ()I 无参返回int）
        属性个数（2个字节）：00 01（1个）
            属性名称索引（2个字节）：00 09（#9 Code）
            属性长度（4个字节）：00 00 00 2F（47）
            属性信息：
            00 01 00 01 00 00 00 05 2A B4 00 02 AC 00
            00 00 02 00 0A 00 00 00 06 00 01 00 00 00 10 00 0B 00 00 00 0C 00 01 00 00 00 05 00 0C 00 0D 00
            00
            {

                {
                    最大操作栈的深度（2个字节）：00 01（1）
                    局部变量最大数目（2个字节）：00 01（1）
                    方法占用字节数（4个字节）：00 00 00 05（5个）
                    方法体（对应助记符）：
                    2A：aload_0
                    B4：getfield
                    00 02：#2  com/kevin/study/jvm/bytecode/MyTest1.a
                    AC：ireturn
                }
                异常表（2个字节）：00 00（无）
                方法的属性个数（2个字节）：00 02（2个）
                属性信息：
                {
                    属性名称索引（2个字节）：00 0A（#10 LineNumberTable）
                    属性长度（4个字节）：00 00 00 06（6）
                    参数个数（2个字节）：00 01（1个）
                        {
                            字节码偏移量（2个字节）：00 00（0）
                            对应行号（2个字节）：00 10（16行）
                        }
                }，
                {
                    属性名称索引（2个字节）：00 0B（#11 LocalVariableTable）
                    属性长度（4个字节）：00 00 00 0C（12个字节）
                    参数个数（2个字节）：00 01（1个）
                        {
                            开始偏移量（2个字节）：00 00（0）
                            长度（2个字节）：00 05（5）
                            名称索引（2个字节）：00 0C（#12 this）
                            名字描述（2个字节）：00 0D（#13 Lcom/kevin/study/jvm/bytecode/MyTest1）
                            index（2个字节）：00 00
                        }
                }
            }
     }，
     {
        访问类型（2个字节）：00 01（public）
        名称索引（2个字节）：00 10（#16 setA）
        描述符索引（2个字节）：00 11（#17 (I)V int参数，无返回值）
        属性个数（2个字节）：00 01
            属性名称索引（2个字节）：00 09（#9 Code）
            属性长度（4个字节）：00 00 00 3E（62）
            属性信息：
            00 02 00 02 00 00 00 06 2A 1B B5 00 02 B1 00 00 00
            02 00 0A 00 00 00 0A 00 02 00 00 00 14 00 05 00 15 00 0B 00 00 00 16 00 02 00 00 00 06 00 0C 00
            0D 00 00 00 00 00 06 00 05 00 06 00 01
            {
                最大操作栈的深度（2个字节）：00 02（2）
                局部变量最大数目（2个字节）：00 02（2）
                方法占用字节数（4个字节）：00 00 00 06（6）
                方法体（对应助记符）：2A 1B B5 00 02 B1
                {
                    2A：aload_0
                    1B：iload_1
                    B5：putfield
                    00 02：#2 com/kevin/study/jvm/bytecode/MyTest1.a
                    B1:return
                }
                异常表数量（2个字节）：00 00
                方法属性个数（2个字节）：00 02（2个）
                属性信息：
                {
                    属性名称索引（2个字节）：00 0A（#10 LineNumberTable）
                    属性长度（4个字节）：00 00 00 0A（10）
                    参数个数（2个字节）：00 02（2个）
                    {
                        字节码偏移量（2个字节）：00 00
                        对应行号（2个字节）：00 14（20行）
                    }，
                    {
                        字节码偏移量：00 05
                        对应行号（2个字节）：00 15（21行）
                    }
                }，
                {
                    属性名称索引（2个字节）：00 0B（#11 LocalVariableTable）
                    属性长度（4个字节）：00 00 00 16（22）
                    参数个数（2个字节）：00 02（2个）
                    {
                        开始偏移量（2个字节）：00 00
                        长度（2个字节）：00 06
                        名称索引（2个字节）：00 0C（#12 this）
                        描述符（2个字节）：00 0D（#13 Lcom/kevin/study/jvm/bytecode/MyTest1）
                        index（2个字节）：00 00
                    },
                    {
                        开始偏移量（2个字节）：00 00
                        长度（2个字节）：00 06
                        名称索引（2个字节）：00 05（#5 a）
                        描述符（2个字节）：00 06（#6 I）
                        index（2个字节）：00 01
                    }
                }
            }
     }
附加属性个数（2个字节）：00 01（1个）
    属性名称索引（2个字节）：00 12（#18 SourceFile）
    属性长度（4个字节）：00 00 00 02
    属性信息：
    {
        属性名称索引（2个字节）：00 13（#19 MyTest1.java）
    }

